publib/__init__.py
publib/__version__.txt
publib/main.py
publib/stylelib/B&W.mplstyle
publib/stylelib/article.mplstyle
publib/stylelib/article_s.mplstyle
publib/stylelib/basic.mplstyle
publib/stylelib/latex.mplstyle
publib/stylelib/origin.mplstyle
publib/stylelib/poster.mplstyle
publib/stylelib/small.mplstyle
publib/stylelib/talk.mplstyle
publib/test/__init__.py
publib/test/test_functions.py
publib/test/test_tools.py
publib/tools/__init__.py
publib/tools/colors.py
publib/tools/fix.py
publib/tools/tools.py
publib-0.4.0.dist-info/LICENSE
publib-0.4.0.dist-info/METADATA
publib-0.4.0.dist-info/WHEEL
publib-0.4.0.dist-info/top_level.txt
publib-0.4.0.dist-info/RECORD
